msoc/__init__.py
msoc/__main__.py
msoc/exceptions.py
msoc/functions.py
msoc/msoc.py
msoc/sound.py
msoc/engines/__init__.py
msoc/engines/base.py
msoc/engines/hitmo.py
msoc/engines/mp3feel.py
msoc/engines/muzbomb.py
msoc/engines/trekson.py
msoc/engines/zaycev_net.py
msoc-0.1.2.dist-info/METADATA
msoc-0.1.2.dist-info/WHEEL
msoc-0.1.2.dist-info/entry_points.txt
msoc-0.1.2.dist-info/top_level.txt
msoc-0.1.2.dist-info/RECORD
