Metadata-Version: 2.4
Name: msoc
Version: 0.1.2
Summary: Быстрый поисковик музыки
Project-URL: GitHub, https://github.com/paranoik1/msoc
Classifier: Programming Language :: Python :: 3
Classifier: License :: OSI Approved :: MIT License
Classifier: Operating System :: OS Independent
Requires-Python: >=3.12
Requires-Dist: bs4
Requires-Dist: aiohttp
Requires-Dist: lxml
